delphin/__init__.py
delphin/cli.py
delphin/data/athena/2017-03-08/paginators-1.json
delphin/data/athena/2017-03-08/service-2.json
delphin/data/athena/2017-03-08/waiters-2.json
delphin-0.0.2.dist-info/DESCRIPTION.rst
delphin-0.0.2.dist-info/METADATA
delphin-0.0.2.dist-info/RECORD
delphin-0.0.2.dist-info/WHEEL
delphin-0.0.2.dist-info/entry_points.txt
delphin-0.0.2.dist-info/metadata.json
delphin-0.0.2.dist-info/top_level.txt
