Metadata-Version: 2.0
Name: delphin
Version: 0.0.2
Summary: UNKNOWN
Home-page: UNKNOWN
Author: Blake Imsland
Author-email: blake@retroco.de
License: MIT
Platform: UNKNOWN
Requires-Dist: botocore (>=1.5.52)
Requires-Dist: sqlparse
